{
  "data": [
    {
      "id": 406,
      "employee": { "id": 42, "name": "Ahmed Benali", "matricule": "EMP-0042" },
      "period": "Avril 2026",
      "month": 4,
      "year": 2026,
      "gross_salary": 75000,
      "overtime_pay": 2500,
      "deductions": {
        "social_security": 7500,
        "income_tax": 4250,
        "advance_deduction": 5000,
        "absence_deduction": 0
      },
      "net_salary": 60750,
      "status": "validated",
      "pdf_url": "https://api.leopardo-rh.com/storage/payslips/2026-04-42.pdf",
      "validated_at": "2026-04-28T10:00:00Z"
    },
    {
      "id": 405,
      "employee": { "id": 42, "name": "Ahmed Benali", "matricule": "EMP-0042" },
      "period": "Mars 2026",
      "month": 3,
      "year": 2026,
      "gross_salary": 75000,
      "overtime_pay": 0,
      "deductions": {
        "social_security": 7500,
        "income_tax": 4250,
        "advance_deduction": 5000,
        "absence_deduction": 681
      },
      "net_salary": 57569,
      "status": "validated",
      "pdf_url": "https://api.leopardo-rh.com/storage/payslips/2026-03-42.pdf",
      "validated_at": "2026-03-28T09:30:00Z"
    },
    {
      "id": 404,
      "employee": { "id": 42, "name": "Ahmed Benali", "matricule": "EMP-0042" },
      "period": "Février 2026",
      "month": 2,
      "year": 2026,
      "gross_salary": 75000,
      "overtime_pay": 1250,
      "deductions": {
        "social_security": 7500,
        "income_tax": 4250,
        "advance_deduction": 5000,
        "absence_deduction": 0
      },
      "net_salary": 59500,
      "status": "validated",
      "pdf_url": "https://api.leopardo-rh.com/storage/payslips/2026-02-42.pdf",
      "validated_at": "2026-02-26T10:00:00Z"
    },
    {
      "id": 403,
      "employee": { "id": 42, "name": "Ahmed Benali", "matricule": "EMP-0042" },
      "period": "Janvier 2026",
      "month": 1,
      "year": 2026,
      "gross_salary": 75000,
      "overtime_pay": 0,
      "deductions": {
        "social_security": 7500,
        "income_tax": 4250,
        "advance_deduction": 0,
        "absence_deduction": 0
      },
      "net_salary": 63250,
      "status": "validated",
      "pdf_url": "https://api.leopardo-rh.com/storage/payslips/2026-01-42.pdf",
      "validated_at": "2026-01-28T11:00:00Z"
    },
    {
      "id": 402,
      "employee": { "id": 42, "name": "Ahmed Benali", "matricule": "EMP-0042" },
      "period": "Décembre 2025",
      "month": 12,
      "year": 2025,
      "gross_salary": 75000,
      "overtime_pay": 3750,
      "deductions": {
        "social_security": 7500,
        "income_tax": 4250,
        "advance_deduction": 0,
        "absence_deduction": 0
      },
      "net_salary": 67000,
      "status": "validated",
      "pdf_url": "https://api.leopardo-rh.com/storage/payslips/2025-12-42.pdf",
      "validated_at": "2025-12-28T10:00:00Z"
    },
    {
      "id": 401,
      "employee": { "id": 42, "name": "Ahmed Benali", "matricule": "EMP-0042" },
      "period": "Novembre 2025",
      "month": 11,
      "year": 2025,
      "gross_salary": 75000,
      "overtime_pay": 0,
      "deductions": {
        "social_security": 7500,
        "income_tax": 4250,
        "advance_deduction": 0,
        "absence_deduction": 1364
      },
      "net_salary": 61886,
      "status": "validated",
      "pdf_url": "https://api.leopardo-rh.com/storage/payslips/2025-11-42.pdf",
      "validated_at": "2025-11-28T10:00:00Z"
    }
  ],
  "meta": {
    "current_page": 1,
    "last_page": 1,
    "per_page": 12,
    "total": 6
  }
}
